odoo8_addon_sale_comment_template-8.0.1.4.0-py2.7-nspkg.pth
odoo_addons/sale_comment_template/__openerp__.py
odoo_addons/sale_comment_template/sale_order.py
odoo_addons/sale_comment_template/sale_order_view.xml
odoo_addons/sale_comment_template/base_comment_template_view.xml
odoo_addons/sale_comment_template/__init__.py
odoo_addons/sale_comment_template/README.rst
odoo_addons/sale_comment_template/security/ir.model.access.csv
odoo_addons/sale_comment_template/i18n/sale_comment_template.pot
odoo_addons/sale_comment_template/i18n/fr.po
odoo_addons/sale_comment_template/views/report_saleorder.xml
odoo8_addon_sale_comment_template-8.0.1.4.0.dist-info/top_level.txt
odoo8_addon_sale_comment_template-8.0.1.4.0.dist-info/WHEEL
odoo8_addon_sale_comment_template-8.0.1.4.0.dist-info/RECORD
odoo8_addon_sale_comment_template-8.0.1.4.0.dist-info/metadata.json
odoo8_addon_sale_comment_template-8.0.1.4.0.dist-info/DESCRIPTION.rst
odoo8_addon_sale_comment_template-8.0.1.4.0.dist-info/METADATA
odoo8_addon_sale_comment_template-8.0.1.4.0.dist-info/namespace_packages.txt
