Metadata-Version: 2.0
Name: odoo8-addon-sale-comment-template
Version: 8.0.1.4.0
Summary: Comments texts templates on Sale documents
Home-page: UNKNOWN
Author: UNKNOWN
Author-email: UNKNOWN
License: UNKNOWN
Platform: UNKNOWN
Requires-Dist: odoo (<9.0a,>=8.0a)
Requires-Dist: odoo8-addon-invoice-comment-template
Classifier: Programming Language :: Python :: 2.7
Classifier: Framework :: Odoo
